fairchem/applications/cattsunami/DATASET.md
fairchem/applications/cattsunami/README.md
fairchem/applications/cattsunami/__init__.py
fairchem/applications/cattsunami/summary_fig.png
fairchem/applications/cattsunami/core/__init__.py
fairchem/applications/cattsunami/core/autoframe.py
fairchem/applications/cattsunami/core/reaction.py
fairchem/applications/cattsunami/databases/__init__.py
fairchem/applications/cattsunami/databases/desorptions_9Aug23.pkl
fairchem/applications/cattsunami/databases/dissociation_reactions_22May24.pkl
fairchem/applications/cattsunami/databases/transfers_5Sept23.pkl
fairchem/applications/cattsunami/run_validation/run_validation.py
fairchem/applications/cattsunami/run_validation/run_validation.sh
fairchem/applications/cattsunami/run_validation/mapping_files/desorption_mapping.pkl
fairchem/applications/cattsunami/run_validation/mapping_files/dissociation_mapping.pkl
fairchem/applications/cattsunami/run_validation/mapping_files/transfer_mapping.pkl
fairchem/applications/cattsunami/tutorial/adding_a_rxn_to_the_db.ipynb
fairchem/applications/cattsunami/tutorial/dissociation_scheme.png
fairchem_applications_cattsunami-1.1.1.dist-info/METADATA
fairchem_applications_cattsunami-1.1.1.dist-info/WHEEL
fairchem_applications_cattsunami-1.1.1.dist-info/RECORD
