Metadata-Version: 2.4
Name: fairchem-applications-cattsunami
Version: 1.1.1
Summary: Accelerating Transition State Energy Calculations with Pre-trained Graph Neural Networks
Project-URL: repository, http://github.com/Fair-Chem/src/fairchem/applications/cattsunami
Project-URL: documentation, https://fair-chem.github.io/
License: MIT License
Requires-Dist: fairchem-core
Requires-Dist: fairchem-data-oc
